PFAS_SAT_ProcessModels/AD.py
PFAS_SAT_ProcessModels/AdvWWT.py
PFAS_SAT_ProcessModels/Comp.py
PFAS_SAT_ProcessModels/DeepWellInjection.py
PFAS_SAT_ProcessModels/Flow.py
PFAS_SAT_ProcessModels/IncomFlow.py
PFAS_SAT_ProcessModels/Inventory.py
PFAS_SAT_ProcessModels/LandApp.py
PFAS_SAT_ProcessModels/Landfill.py
PFAS_SAT_ProcessModels/ProcessModel.py
PFAS_SAT_ProcessModels/ProcessModelsMetaData.py
PFAS_SAT_ProcessModels/SCWO.py
PFAS_SAT_ProcessModels/Stab.py
PFAS_SAT_ProcessModels/SubProcesses.py
PFAS_SAT_ProcessModels/SurfaceWaterRelease.py
PFAS_SAT_ProcessModels/ThermalReactivation.py
PFAS_SAT_ProcessModels/ThermalTreatment.py
PFAS_SAT_ProcessModels/WWT.py
PFAS_SAT_ProcessModels/__init__.py
PFAS_SAT_ProcessModels-0.0.4.dist-info/AUTHORS.rst
PFAS_SAT_ProcessModels-0.0.4.dist-info/LICENSE.md
PFAS_SAT_ProcessModels-0.0.4.dist-info/METADATA
PFAS_SAT_ProcessModels-0.0.4.dist-info/WHEEL
PFAS_SAT_ProcessModels-0.0.4.dist-info/top_level.txt
PFAS_SAT_ProcessModels-0.0.4.dist-info/RECORD
